jvincipy/__init__.py
jvincipy/cli.py
jvincipy/core.py
jvincipy/css.py
jvincipy/tags.py
jvincipy-1.0.2.dist-info/licenses/LICENSE
jvincipy-1.0.2.dist-info/METADATA
jvincipy-1.0.2.dist-info/WHEEL
jvincipy-1.0.2.dist-info/entry_points.txt
jvincipy-1.0.2.dist-info/top_level.txt
jvincipy-1.0.2.dist-info/RECORD
