Metadata-Version: 2.4
Name: jvincipy
Version: 1.0.2
Summary: A Python DSL to write HTML using Python objects
Author-email: Jeevan N <njeevan2216@gmail.com>
License: MIT
Project-URL: Homepage, https://github.com/nj2216/jvincipy
Project-URL: Repository, https://github.com/nj2216/jvincipy
Project-URL: Issues, https://github.com/nj2216/jvincipy/issues
Classifier: Programming Language :: Python :: 3
Classifier: License :: OSI Approved :: MIT License
Classifier: Operating System :: OS Independent
Requires-Python: >=3.8
License-File: LICENSE
Dynamic: license-file
